shopping_list_generator/__init__.py
shopping_list_generator/__main__.py
shopping_list_generator/parsingutils.py
shopping_list_generator/recipe.py
shopping_list_generator/recipelocator.py
shopping_list_generator/shoppinglist.py
shopping_list_generator-0.0.7.dist-info/METADATA
shopping_list_generator-0.0.7.dist-info/WHEEL
shopping_list_generator-0.0.7.dist-info/entry_points.txt
shopping_list_generator-0.0.7.dist-info/top_level.txt
shopping_list_generator-0.0.7.dist-info/RECORD
