Metadata-Version: 2.1
Name: shopping-list-generator
Version: 0.0.7
Summary: Generate a shopping list from recipe .txt files
Home-page: https://github.com/CallumHoughton18/shopping-list-generator
Author: Callum Houghton
Author-email: callum.houghton13@hotmail.co.uk
License: MIT
Platform: UNKNOWN
Classifier: License :: OSI Approved :: MIT License
Classifier: Programming Language :: Python :: 3
Classifier: Programming Language :: Python :: 3.7
